{
    "items": [
        { "character": "あ", "probability": 1672 },
        { "character": "か", "probability": 3518 },
        { "character": "さ", "probability": 1067 },
        { "character": "た", "probability": 3075 },
        { "character": "な", "probability": 2724 },
        { "character": "は", "probability": 2493 },
        { "character": "ま", "probability": 1307 },
        { "character": "や", "probability": 527 },
        { "character": "ら", "probability": 1563 },
        { "character": "わ", "probability": 2445 },
        { "character": "い", "probability": 6653 },
        { "character": "き", "probability": 2386 },
        { "character": "し", "probability": 4571 },
        { "character": "ち", "probability": 1240 },
        { "character": "に", "probability": 3062 },
        { "character": "ひ", "probability": 541 },
        { "character": "み", "probability": 784 },
        { "character": "ゆ", "probability": 310 },
        { "character": "り", "probability": 1804 },
        { "character": "を", "probability": 10 },
        { "character": "う", "probability": 5095 },
        { "character": "く", "probability": 2563 },
        { "character": "す", "probability": 1611 },
        { "character": "つ", "probability": 1411 },
        { "character": "ぬ", "probability": 22 },
        { "character": "ふ", "probability": 554 },
        { "character": "む", "probability": 349 },
        { "character": "よ", "probability": 1115 },
        { "character": "る", "probability": 2376 },
        { "character": "ん", "probability": 400 },
        { "character": "え", "probability": 696 },
        { "character": "け", "probability": 1169 },
        { "character": "せ", "probability": 1414 },
        { "character": "て", "probability": 2499 },
        { "character": "ね", "probability": 367 },
        { "character": "へ", "probability": 272 },
        { "character": "め", "probability": 904 },
        { "character": "れ", "probability": 3045 },
        { "character": "お", "probability": 1080 },
        { "character": "こ", "probability": 2456 },
        { "character": "そ", "probability": 1101 },
        { "character": "と", "probability": 3227 },
        { "character": "の", "probability": 4022 },
        { "character": "ほ", "probability": 531 },
        { "character": "も", "probability": 1669 },
        { "character": "ろ", "probability": 497 },
        { "character": "が", "probability": 2008 },
        { "character": "ざ", "probability": 196 },
        { "character": "だ", "probability": 1244 },
        { "character": "ば", "probability": 530 },
        { "character": "ぎ", "probability": 451 },
        { "character": "じ", "probability": 1523 },
        { "character": "ぢ", "probability": 0 },
        { "character": "び", "probability": 358 },
        { "character": "ぐ", "probability": 155 },
        { "character": "ず", "probability": 186 },
        { "character": "づ", "probability": 102 },
        { "character": "ぶ", "probability": 317 },
        { "character": "げ", "probability": 389 },
        { "character": "ぜ", "probability": 284 },
        { "character": "で", "probability": 1806 },
        { "character": "べ", "probability": 273 },
        { "character": "ご", "probability": 268 },
        { "character": "ぞ", "probability": 127 },
        { "character": "ど", "probability": 759 },
        { "character": "ぼ", "probability": 171 },
        { "character": "ぱ", "probability": 80 },
        { "character": "ぴ", "probability": 28 },
        { "character": "ぷ", "probability": 103 },
        { "character": "ぺ", "probability": 37 },
        { "character": "ぽ", "probability": 135 }
    ]
}